cookclient/__init__.py
cookclient/containers.py
cookclient/instance.py
cookclient/jobs.py
cookclient/util.py
cook_client_api-0.3.5.dist-info/METADATA
cook_client_api-0.3.5.dist-info/WHEEL
cook_client_api-0.3.5.dist-info/top_level.txt
cook_client_api-0.3.5.dist-info/RECORD
