Metadata-Version: 2.1
Name: cook-client-api
Version: 0.3.5
Summary: Cook Scheduler Client API for Python
Home-page: https://github.com/twosigma/Cook
License: UNKNOWN
Platform: UNKNOWN
Classifier: Development Status :: 3 - Alpha
Classifier: Programming Language :: Python :: 3
Classifier: License :: OSI Approved :: Apache Software License
Classifier: Operating System :: OS Independent
Requires-Python: >=3.6
Requires-Dist: requests
